__init__.py
xhashtagAI.py
xhashtagAI-0.1.0.dist-info/METADATA
xhashtagAI-0.1.0.dist-info/WHEEL
xhashtagAI-0.1.0.dist-info/entry_points.txt
xhashtagAI-0.1.0.dist-info/top_level.txt
xhashtagAI-0.1.0.dist-info/RECORD
