Metadata-Version: 2.1
Name: xhashtagAI
Version: 0.1.0
Author: Thanabordee N. (Noun)
Author-email: thanabordee.noun@gmail.com
Requires-Dist: openai
